Workbook

Sheet Inputs
A1: AI Learning Platform — 成本模型 Inputs（黃底藍字＝可調）
A3: 參數 | B3: 值 | C3: 單位 | D3: 說明 / 來源
A4: FX_USD_TWD | B4: 32 | C4: NT$/US$ | D4: 匯率假設
A5: 售價 / 堂 (1對1) | B5: 600 | C5: NT$ | D5: 使用者指定
A6: 老師分潤 | B6: 0.7 | C6: % | D6: 使用者指定；程式現況為 100%，P0 才實作抽成
A7: 金流手續費率 | B7: 0.028 | C7: % | D7: 約 2.8%，多閘道平均
A8: 課堂長度 | B8: 50 | C8: min | D8: 課程/成本單位，非 AI 分析單位
A9: 每堂 participant-min (1對1) | B9: 100 | C9: min | D9: 2 人 × 50 分
A10: —— RTC 碼率 ——
A11: 720p 碼率 | B11: 1.5 | C11: Mbps | D11: Agora high 預設 1.2–1.8，取 1.5
A12: 360p 碼率 | B12: 0.5 | C12: Mbps | D12: medium 預設
A13: 純音訊碼率 | B13: 0.04 | C13: Mbps | D13: opus ~40kbps
A14: —— 供應商單價 ——
A15: Agora HD /1k min | B15: 3.99 | C15: US$ | D15: 訂閱聚合解析度 ≤921,600px
A16: Agora 2K /1k min | B16: 15.99 | C16: US$ | D16: ≤3,686,400px
A17: Agora 2K+ /1k min | B17: 35.99 | C17: US$ | D17: >3,686,400px
A18: Agora Audio /1k min | B18: 0.99 | C18: US$ | D18: 只訂閱音訊
A19: Netless 白板 /1k min | B19: 1.4 | C19: US$ | D19: 官方價；repo 另有 0.0125/0.38 說法，待帳單校準
A20: Cloudflare SFU /GB | B20: 0.05 | C20: US$ | D20: 僅 CF→client 出流
A21: CF 免費額度 | B21: 1000 | C21: GB/月 | D21: SFU+TURN 共用
A22: Agora 免費額度 | B22: 10000 | C22: min/月 | D22: 買套餐即失效
A23: —— AI 每堂 (1對1) ——
A24: AI Learning /堂 | B24: 3.65 | C24: NT$ | D24: L1+L2+L3+L4+Tutor+Assess+Copilot+儲存（thinking 關）
A25: AI Learning /堂 (對話型) | B25: 4.6 | C25: NT$ | D25: L1 90–100 段 + Review + Lambda
A26: AI 硬上限 /堂 | B26: 12 | C26: NT$ | D26: 觸頂走降級階梯
A27: —— 其他每堂 ——
A28: 變動基礎設施 /堂 | B28: 1.3 | C28: NT$ | D28: DynamoDB/Lambda/Hosting 變動部分
A29: 儲存 /堂 | B29: 0.05 | C29: NT$ | D29: 音訊/逐字稿/快照，30天保存
A30: —— 規模模型參數 ——
A31: 每月每週比 (週→月) | B31: 4.33 | C31: × | D31: 52/12
A32: Agora 回退比例 | B32: 0.05 | C32: % | D32: B 情境混合 RTC 用；0=全 CF
A35: 圖例：黃底藍字＝可調輸入；黑字＝公式；改 Inputs 全表重算。

Sheet RTC per-lesson
A1: §5 每堂 1對1 RTC 成本（100 participant-min）
A2: GB 公式：Mbps ÷ 8 × 秒 ÷ 1000（Cloudflare 按十進位 GB 計費，雙向出流從 SFU 各計一次）
A4: 模式 | B4: 出流 GB | C4: Agora US$ | D4: CF US$ | E4: Agora NT$ | F4: CF NT$ | G4: 備註
A5: 雙方 720p | B5: =Inputs!$B$11/8*(Inputs!$B$8*60)/1000*2 | C5: =Inputs!$B$9/1000*Inputs!$B$15 | D5: =B5*Inputs!$B$20 | E5: =C5*Inputs!$B$4 | F5: =D5*Inputs!$B$4 | G5: Agora HD；main 現況
A6: 師720p+生360p | B6: =(Inputs!$B$11+Inputs!$B$12)/8*(Inputs!$B$8*60)/1000 | C6: =Inputs!$B$9/1000*Inputs!$B$15 | D6: =B6*Inputs!$B$20 | E6: =C6*Inputs!$B$4 | F6: =D6*Inputs!$B$4 | G6: Agora 仍 HD 同價
A7: 雙方 360p (CF 預設) | B7: =Inputs!$B$12/8*(Inputs!$B$8*60)/1000*2 | C7: =Inputs!$B$9/1000*Inputs!$B$15 | D7: =B7*Inputs!$B$20 | E7: =C7*Inputs!$B$4 | F7: =D7*Inputs!$B$4 | G7: Agora 仍 HD 同價（省不到）
A8: 師720p+生純音訊 | B8: =(Inputs!$B$11+Inputs!$B$13)/8*(Inputs!$B$8*60)/1000 | C8: =(Inputs!$B$9/2/1000*Inputs!$B$15)+(Inputs!$B$9/2/1000*Inputs!$B$18) | D8: =B8*Inputs!$B$20 | E8: =C8*Inputs!$B$4 | F8: =D8*Inputs!$B$4 | G8: 老師訂閱音訊，省~37%
A10: Netless 白板 /堂 | C10: =Inputs!$B$9/1000*Inputs!$B$19 | E10: =C10*Inputs!$B$4 | G10: 2人×50min×1.4/1k（按 participant-min）
A11: 小班1師4生 Agora現況(全720p互訂) | C11: =250/1000*Inputs!$B$16 | E11: =C11*Inputs!$B$4 | G11: 每人訂4×720p→2K級 $15.99
A12: 小班1師4生 CF | B12: =((Inputs!$B$11/8*3000/1000*4)+(Inputs!$B$12/8*3000/1000*4))/1 | D12: =B12*Inputs!$B$20 | F12: =D12*Inputs!$B$4 | G12: 生只訂老師+生上行360p

Sheet UnitEcon (§10)
A1: §10 每堂 Unit Economics（1對1，NT$）
A3: 項目 | B3: A 現況 Agora 無AI | C3: A′ CF 無AI | D3: B CF+AI | E3: B-Agora +AI
A4: Revenue | B4: Inputs!$B$5 | C4: Inputs!$B$5 | D4: Inputs!$B$5 | E4: Inputs!$B$5
A5: 老師分潤 | B5: =-Inputs!$B$5*Inputs!$B$6 | C5: =-Inputs!$B$5*Inputs!$B$6 | D5: =-Inputs!$B$5*Inputs!$B$6 | E5: =-Inputs!$B$5*Inputs!$B$6
A6: 金流手續費 | B6: =-Inputs!$B$5*Inputs!$B$7 | C6: =-Inputs!$B$5*Inputs!$B$7 | D6: =-Inputs!$B$5*Inputs!$B$7 | E6: =-Inputs!$B$5*Inputs!$B$7
A7: RTC(含白板) | B7: =-('RTC per-lesson'!$E$5+'RTC per-lesson'!$E$10) | C7: =-'RTC per-lesson'!$F$7 | D7: =-'RTC per-lesson'!$F$7 | E7: =-('RTC per-lesson'!$E$5+'RTC per-lesson'!$E$10)
A8: AI Learning | B8: 0 | C8: 0 | D8: =-Inputs!$B$24 | E8: =-Inputs!$B$24
A9: 儲存 | B9: 0 | C9: 0 | D9: =-Inputs!$B$29 | E9: =-Inputs!$B$29
A10: 基礎設施(變動) | B10: =-Inputs!$B$28 | C10: =-Inputs!$B$28 | D10: =-Inputs!$B$28 | E10: =-Inputs!$B$28
A11: Platform Contribution | B11: =SUM(B4:B10) | C11: =SUM(C4:C10) | D11: =SUM(D4:D10) | E11: =SUM(E4:E10)
A12: 貢獻率 | B12: =B11/Inputs!$B$5 | C12: =C11/Inputs!$B$5 | D12: =D11/Inputs!$B$5 | E12: =E11/Inputs!$B$5
A14: 校正項（列為參數，未計入上表；見計畫 §10）
A15: Agora 回退混合 RTC(f) | B15: =(1-Inputs!$B$32)*'RTC per-lesson'!$F$7+Inputs!$B$32*('RTC per-lesson'!$E$5+'RTC per-lesson'!$E$10) | C15: 回退率見 Inputs
A16: 營業稅 5%(若含稅) | B16: =-Inputs!$B$5*0.05/1.05 | C16: 若 NT$600 為含稅價，營收含稅

Sheet Scale (§11)
A1: §11 規模模型（1對1，每週 2 堂，NT$/月）
A2: 週堂數(可調) | B2: 2
A4: 學生 | B4: 堂數/月 | C4: Revenue | D4: Teacher | E4: 金流 | F4: RTC-Agora | G4: RTC-CF | H4: AI | I4: 固定+變動基礎設施 | J4: GP 情境A(Agora無AI) | K4: GP 情境B(CF+AI)
A5: 20 | B5: =A5*$B$2*Inputs!$B$31 | C5: =B5*Inputs!$B$5 | D5: =C5*Inputs!$B$6 | E5: =C5*Inputs!$B$7 | F5: =MAX(0,B5*Inputs!$B$9-Inputs!$B$22)/1000*Inputs!$B$15*Inputs!$B$4+B5*'RTC per-lesson'!$E$10 | G5: =MAX(0,B5*'RTC per-lesson'!$B$7-Inputs!$B$21)*Inputs!$B$20*Inputs!$B$4 | H5: =B5*Inputs!$B$24 | I5: =B5*Inputs!$B$28+=IF(B5<=1000,3200,IF(B5<=5000,6400,IF(B5<=10000,9600,16000))) | J5: =C5-D5-E5-F5-I5 | K5: =C5-D5-E5-G5-H5-I5
A6: 50 | B6: =A6*$B$2*Inputs!$B$31 | C6: =B6*Inputs!$B$5 | D6: =C6*Inputs!$B$6 | E6: =C6*Inputs!$B$7 | F6: =MAX(0,B6*Inputs!$B$9-Inputs!$B$22)/1000*Inputs!$B$15*Inputs!$B$4+B6*'RTC per-lesson'!$E$10 | G6: =MAX(0,B6*'RTC per-lesson'!$B$7-Inputs!$B$21)*Inputs!$B$20*Inputs!$B$4 | H6: =B6*Inputs!$B$24 | I6: =B6*Inputs!$B$28+=IF(B6<=1000,3200,IF(B6<=5000,6400,IF(B6<=10000,9600,16000))) | J6: =C6-D6-E6-F6-I6 | K6: =C6-D6-E6-G6-H6-I6
A7: 100 | B7: =A7*$B$2*Inputs!$B$31 | C7: =B7*Inputs!$B$5 | D7: =C7*Inputs!$B$6 | E7: =C7*Inputs!$B$7 | F7: =MAX(0,B7*Inputs!$B$9-Inputs!$B$22)/1000*Inputs!$B$15*Inputs!$B$4+B7*'RTC per-lesson'!$E$10 | G7: =MAX(0,B7*'RTC per-lesson'!$B$7-Inputs!$B$21)*Inputs!$B$20*Inputs!$B$4 | H7: =B7*Inputs!$B$24 | I7: =B7*Inputs!$B$28+=IF(B7<=1000,3200,IF(B7<=5000,6400,IF(B7<=10000,9600,16000))) | J7: =C7-D7-E7-F7-I7 | K7: =C7-D7-E7-G7-H7-I7
A8: 500 | B8: =A8*$B$2*Inputs!$B$31 | C8: =B8*Inputs!$B$5 | D8: =C8*Inputs!$B$6 | E8: =C8*Inputs!$B$7 | F8: =MAX(0,B8*Inputs!$B$9-Inputs!$B$22)/1000*Inputs!$B$15*Inputs!$B$4+B8*'RTC per-lesson'!$E$10 | G8: =MAX(0,B8*'RTC per-lesson'!$B$7-Inputs!$B$21)*Inputs!$B$20*Inputs!$B$4 | H8: =B8*Inputs!$B$24 | I8: =B8*Inputs!$B$28+=IF(B8<=1000,3200,IF(B8<=5000,6400,IF(B8<=10000,9600,16000))) | J8: =C8-D8-E8-F8-I8 | K8: =C8-D8-E8-G8-H8-I8
A9: 1000 | B9: =A9*$B$2*Inputs!$B$31 | C9: =B9*Inputs!$B$5 | D9: =C9*Inputs!$B$6 | E9: =C9*Inputs!$B$7 | F9: =MAX(0,B9*Inputs!$B$9-Inputs!$B$22)/1000*Inputs!$B$15*Inputs!$B$4+B9*'RTC per-lesson'!$E$10 | G9: =MAX(0,B9*'RTC per-lesson'!$B$7-Inputs!$B$21)*Inputs!$B$20*Inputs!$B$4 | H9: =B9*Inputs!$B$24 | I9: =B9*Inputs!$B$28+=IF(B9<=1000,3200,IF(B9<=5000,6400,IF(B9<=10000,9600,16000))) | J9: =C9-D9-E9-F9-I9 | K9: =C9-D9-E9-G9-H9-I9
A11: 註：Agora 大量可談折扣；GPU/Media 以點數收費毛利≥60%，不在此表。

Sheet Breakeven (§12)
A1: §12 損益兩平（情境 B）
A3: 每堂貢獻(情境B,NT$) | B3: ='UnitEcon (§10)'!$D$11
A4: 月固定成本(可調) | B4: 300000
A6: 週堂數→ | B6: 1 | C6: 2 | D6: 4 | E6: 8
A7: Break-even 學生數 | B7: =ROUNDUP($B$4/($B$3*1*Inputs!$B$31),0) | C7: =ROUNDUP($B$4/($B$3*2*Inputs!$B$31),0) | D7: =ROUNDUP($B$4/($B$3*4*Inputs!$B$31),0) | E7: =ROUNDUP($B$4/($B$3*8*Inputs!$B$31),0)
A9: 只算技術固定費 NT$3,200 時 | B9: =ROUNDUP(3200/($B$3*2*Inputs!$B$31),0) | C9: 位學生(每週2堂)即打平
A11: AI 每堂占貢獻比 | B11: =Inputs!$B$24/$B$3 | C11: AI 提升續課/客單超過此比例即回本
